niftiview_app/__init__.py
niftiview_app/data/config.json
niftiview_app/data/niftiview.icns
niftiview_app/data/niftiview.ico
niftiview_app/data/niftiview.png
niftiview_app/main.py
niftiview_app/utils.py
niftiview_app-1.0.2.dist-info/LICENSE
niftiview_app-1.0.2.dist-info/METADATA
niftiview_app-1.0.2.dist-info/WHEEL
niftiview_app-1.0.2.dist-info/entry_points.txt
niftiview_app-1.0.2.dist-info/RECORD
