Metadata-Version: 2.1
Name: niftiview-app
Version: 1.0.2
Summary: Standalone app for viewing volumetric images 🧠 based on Python
Home-page: https://github.com/codingfisch/niftiview-app
License: MIT
Author: codingfisch
Author-email: l_fisc17@wwu.de
Requires-Python: >=3.9,<4.0
Classifier: Intended Audience :: Science/Research
Classifier: License :: OSI Approved :: MIT License
Classifier: Operating System :: OS Independent
Classifier: Programming Language :: Python :: 3
Classifier: Programming Language :: Python :: 3.9
Classifier: Programming Language :: Python :: 3.10
Classifier: Programming Language :: Python :: 3.11
Classifier: Programming Language :: Python :: 3.12
Classifier: Programming Language :: Python :: 3.13
Requires-Dist: dcm2niix
Requires-Dist: niftiview (>=1.0.0)
Requires-Dist: sv-ttk
Requires-Dist: tkinterdnd2 ; sys_platform != "darwin"
Requires-Dist: tkinterdnd2-universal ; sys_platform == "darwin"
Project-URL: Repository, https://github.com/codingfisch/niftiview-app
